{
    "msg": "",
    "total": 1,
    "data": [
        {
            "redirect": "/business-pages",
            "path": "/",
            "component": "/home",
            "level": "",
            "children": [
                {
                    "redirect": "/business-pages/index",
                    "path": "business-pages",
                    "component": "main-layout",
                    "level": "",
                    "children": [
                        {
                            "redirect": "",
                            "path": "index",
                            "component": "/business-pages/index",
                            "level": "",
                            "children": [],
                            "meta": {
                                "hidden": "true",
                                "icon": "pie-chart",
                                "title": "统计"
                            },
                            "query": "",
                            "name": "businessPagesIndex"
                        }
                    ],
                    "meta": {
                        "hidden": "true",
                        "icon": "appstore",
                        "title": "工作台"
                    },
                    "query": "",
                    "name": "businessPages"
                },
                {
                    "redirect": "",
                    "path": "test",
                    "component": "/test/index",
                    "level": "",
                    "children": [],
                    "meta": {
                        "hidden": "true",
                        "icon": "exclamation",
                        "title": "一级菜单"
                    },
                    "query": "",
                    "name": "test"
                },
                {
                    "redirect": "/not-page/index",
                    "path": "not-page",
                    "component": "main-layout",
                    "level": "",
                    "children": [
                        {
                            "redirect": "",
                            "path": "index",
                            "component": "/not-page/index",
                            "level": "",
                            "children": [],
                            "meta": {
                                "hidden": "true",
                                "icon": "api",
                                "title": "404"
                            },
                            "query": "",
                            "name": "not-page"
                        }
                    ],
                    "meta": {
                        "hidden": "true",
                        "icon": "file-exclamation",
                        "title": "异常页"
                    },
                    "query": "",
                    "name": "specialPages"
                }
            ],
            "meta": {
                "hidden": "true",
                "icon": "",
                "title": "主页"
            },
            "query": "",
            "name": "home"
        }
    ],
    "success": true
}